fn_station/__init__.py
fn_station/_json.py
fn_station/blueprint.py
fn_station/queries.py
fn_station/query_storage.py
fn_station/static/fn_station/favicon.ico
fn_station/static/fn_station/fontawesome/LICENSE.txt
fn_station/static/fn_station/fontawesome/css/all.css
fn_station/static/fn_station/fontawesome/css/all.min.css
fn_station/static/fn_station/fontawesome/css/brands.css
fn_station/static/fn_station/fontawesome/css/brands.min.css
fn_station/static/fn_station/fontawesome/css/fontawesome.css
fn_station/static/fn_station/fontawesome/css/fontawesome.min.css
fn_station/static/fn_station/fontawesome/css/regular.css
fn_station/static/fn_station/fontawesome/css/regular.min.css
fn_station/static/fn_station/fontawesome/css/solid.css
fn_station/static/fn_station/fontawesome/css/solid.min.css
fn_station/static/fn_station/fontawesome/css/svg-with-js.css
fn_station/static/fn_station/fontawesome/css/svg-with-js.min.css
fn_station/static/fn_station/fontawesome/css/v4-shims.css
fn_station/static/fn_station/fontawesome/css/v4-shims.min.css
fn_station/static/fn_station/fontawesome/js/all.js
fn_station/static/fn_station/fontawesome/js/all.min.js
fn_station/static/fn_station/fontawesome/js/brands.js
fn_station/static/fn_station/fontawesome/js/brands.min.js
fn_station/static/fn_station/fontawesome/js/conflict-detection.js
fn_station/static/fn_station/fontawesome/js/conflict-detection.min.js
fn_station/static/fn_station/fontawesome/js/fontawesome.js
fn_station/static/fn_station/fontawesome/js/fontawesome.min.js
fn_station/static/fn_station/fontawesome/js/regular.js
fn_station/static/fn_station/fontawesome/js/regular.min.js
fn_station/static/fn_station/fontawesome/js/solid.js
fn_station/static/fn_station/fontawesome/js/solid.min.js
fn_station/static/fn_station/fontawesome/js/v4-shims.js
fn_station/static/fn_station/fontawesome/js/v4-shims.min.js
fn_station/static/fn_station/fontawesome/less/_animated.less
fn_station/static/fn_station/fontawesome/less/_bordered-pulled.less
fn_station-0.5.0.dist-info/WHEEL
fn_station-0.5.0.dist-info/METADATA
fn_station-0.5.0.dist-info/RECORD
