Metadata-Version: 2.1
Name: fn-station
Version: 0.5.0
Summary: 
Author: James Saunders
Author-email: james@businessoptics.biz
Requires-Python: >=3.7,<4.0
Classifier: Programming Language :: Python :: 3
Classifier: Programming Language :: Python :: 3.7
Classifier: Programming Language :: Python :: 3.8
Requires-Dist: flask-scss (>=0.5,<0.6)
Requires-Dist: fn_graph_studio
Requires-Dist: instant_api
Requires-Dist: psycopg2 (>=2.8.4,<3.0.0)
Requires-Dist: sqlalchemy (>=1.3.13,<2.0.0)
